LICENSE.txt
README.md
setup.py
twilio-stubs/__init__.py
twilio-stubs/__init__.pyi
twilio-stubs/request_validator.pyi
twilio-stubs/base/__init__.pyi
twilio-stubs/base/deserialize.pyi
twilio-stubs/base/domain.pyi
twilio-stubs/base/exceptions.pyi
twilio-stubs/base/instance_context.pyi
twilio-stubs/base/instance_resource.pyi
twilio-stubs/base/list_resource.pyi
twilio-stubs/base/obsolete.pyi
twilio-stubs/base/page.pyi
twilio-stubs/base/serialize.pyi
twilio-stubs/base/values.pyi
twilio-stubs/base/version.pyi
twilio-stubs/http/__init__.pyi
twilio-stubs/http/http_client.pyi
twilio-stubs/http/request.pyi
twilio-stubs/http/response.pyi
twilio-stubs/http/validation_client.pyi
twilio-stubs/jwt/__init__.pyi
twilio-stubs/jwt/access_token/__init__.pyi
twilio-stubs/jwt/access_token/grants.pyi
twilio-stubs/jwt/client/__init__.pyi
twilio-stubs/jwt/taskrouter/__init__.pyi
twilio-stubs/jwt/taskrouter/capabilities.pyi
twilio-stubs/jwt/validation/__init__.pyi
twilio-stubs/rest/__init__.pyi
twilio-stubs/rest/accounts/__init__.pyi
twilio-stubs/rest/accounts/v1/__init__.pyi
twilio-stubs/rest/accounts/v1/auth_token_promotion.pyi
twilio-stubs/rest/accounts/v1/secondary_auth_token.pyi
twilio-stubs/rest/accounts/v1/credential/__init__.pyi
twilio-stubs/rest/accounts/v1/credential/aws.pyi
twilio-stubs/rest/accounts/v1/credential/public_key.pyi
twilio-stubs/rest/api/__init__.pyi
twilio-stubs/rest/api/v2010/__init__.pyi
twilio-stubs/rest/api/v2010/account/__init__.pyi
twilio-stubs/rest/api/v2010/account/application.pyi
twilio-stubs/rest/api/v2010/account/authorized_connect_app.pyi
twilio-stubs/rest/api/v2010/account/balance.pyi
twilio-stubs/rest/api/v2010/account/connect_app.pyi
twilio-stubs/rest/api/v2010/account/key.pyi
twilio-stubs/rest/api/v2010/account/new_key.pyi
twilio-stubs/rest/api/v2010/account/new_signing_key.pyi
twilio-stubs/rest/api/v2010/account/notification.pyi
twilio-stubs/rest/api/v2010/account/outgoing_caller_id.pyi
twilio-stubs/rest/api/v2010/account/short_code.pyi
twilio_stubs.egg-info/PKG-INFO
twilio_stubs.egg-info/SOURCES.txt
twilio_stubs.egg-info/dependency_links.txt
twilio_stubs.egg-info/not-zip-safe
twilio_stubs.egg-info/requires.txt
twilio_stubs.egg-info/top_level.txt